{"files":{"asi.fs.glsl":47,"asi.shader.json":48,"asi.vs.glsl":49,"barrel_blur.fs.glsl":50,"barrel_blur.shader.json":51,"blendnotest.vs.glsl":52,"blend_notest.shader.json":53,"bloom.fs.glsl":54,"bloom.shader.json":55,"blur.fs.glsl":56,"blur.shader.json":57,"contort.fs.glsl":58,"contort.shader.json":59,"diffuse.fs.glsl":60,"diffuse.shader.json":61,"diffuse.vs.glsl":62,"diffuse_bothside.shader.json":63,"diffuse_nolight.fs.glsl":64,"diffuse_nolight.shader.json":65,"diffuse_nolight.vs.glsl":66,"diffuse_nolight_bothside.shader.json":67,"dof.fs.glsl":68,"dof.shader.json":69,"f14trans.fs.glsl":70,"f14trans.vs.glsl":71,"f4skin.fs.glsl":72,"f4skin.shader.json":73,"f4skin.vs.glsl":74,"fakepbr.fs.glsl":75,"fakepbr.shader.json":76,"fakepbr.vs.glsl":77,"filter_quad.fs.glsl":78,"filter_quad.shader.json":79,"flowwater_new.fs.glsl":80,"flowwater_new.shader.json":81,"flowwater_new.vs.glsl":82,"gaussianBlur.fs.glsl":83,"gaussianBlur.shader.json":84,"hdr_quad.shader.json":85,"hdr_quad_0.fs.glsl":86,"hdr_quad_1.fs.glsl":87,"light1.fs.glsl":88,"light1.shader.json":89,"light1.vs.glsl":90,"light2.fs.glsl":91,"light2.shader.json":92,"light2.vs.glsl":93,"light3.fs.glsl":94,"light3.shader.json":95,"light3.vs.glsl":96,"linetrail.fs.glsl":97,"linetrail.shader.json":98,"linetrail.vs.glsl":99,"mask_add_tint.shader.json":100,"mask_add_tint_uvroll.shader.json":101,"mask_blend_tint.shader.json":102,"mask_blend_tint_uvroll.shader.json":103,"mask_trans_tint.fs.glsl":104,"mask_trans_tint.vs.glsl":105,"mosaic.fs.glsl":106,"mosaic.shader.json":107,"normalmap.fs.glsl":108,"normalmap.shader.json":109,"normalmap.vs.glsl":110,"outline.fs.glsl":111,"outline.shader.json":112,"particlesystem.fs.glsl":113,"particlesystem.vs.glsl":114,"particlesystem_additive.shader.json":115,"particlesystem_additive_transparent_particles_standard.shader.json":193,"particlesystem_alphablended.shader.json":117,"particlesystem_alphablended_transparent_particles_standard.shader.json":194,"particlesystem_transparent_particles_standard.fs.glsl":195,"particlesystem_transparent_particles_standard.vs.glsl":120,"particles_add.shader.json":121,"particles_add_notest.shader.json":122,"particles_blend.shader.json":123,"particles_blend_notest.shader.json":124,"particles_diffuse.shader.json":125,"particle_mask_add_tint.shader.json":126,"particle_mask_blend_tint.shader.json":127,"par_mask_tint.fs.glsl":128,"par_mask_tint.vs.glsl":129,"pbr.fs.glsl":130,"pbr.shader.json":131,"pbr.vs.glsl":132,"pbrMR.fs.glsl":133,"pbrMR.shader.json":134,"pbrMR.vs.glsl":135,"pbr_sss.fs.glsl":136,"pbr_sss.shader.json":137,"pbr_sss.vs.glsl":138,"post_depth.fs.glsl":139,"post_depth.vs.glsl":140,"quad.vs.glsl":141,"radial_blur.fs.glsl":142,"radial_blur.shader.json":143,"separate_blur.fs.glsl":144,"separate_blur.shader.json":145,"separate_blur.vs.glsl":146,"shadowmap.fs.glsl":147,"shadowmap.shader.json":148,"shadowmap.vs.glsl":149,"simple.fs.glsl":150,"simple.shader.json":151,"simple.vs.glsl":152,"skybox.fs.glsl":153,"skybox.shader.json":154,"skybox.vs.glsl":155,"sssss.fs.glsl":156,"sssss.shader.json":157,"sssss.vs.glsl":158,"streamlight.fs.glsl":159,"streamlight.shader.json":160,"streamlight.vs.glsl":161,"streamlight_bothside.shader.json":162,"terrain.fs.glsl":163,"terrain.shader.json":164,"terrain.vs.glsl":165,"testtexuv.fs.glsl":166,"testtexuv.shader.json":167,"testtexuv.vs.glsl":168,"transparent.fs.glsl":169,"transparent.shader.json":170,"transparent.vs.glsl":171,"transparent_particles_standard.fs.glsl":195,"transparent_particles_standard.shader.json":196,"transparent_particles_standard.vs.glsl":173,"vignetting.fs.glsl":174,"vignetting.shader.json":175},"pkg":["MainShader.jpkg.json"]}