{"tag":"KeyFrameAnimtionClip by unity export <v1.00>","frameRate":60,"length":1,"wrapMode":2,"curves":[{"path":"","type":"UnityEngine.Transform","propertyName":"m_LocalPosition.x","keyFrames":[{"inTangent":-7.6100001335144,"outTangent":-7.6100001335144,"tangentMode":10,"time":0,"value":-0.469999998807907},{"inTangent":-7.6100001335144,"outTangent":-7.6100001335144,"tangentMode":10,"time":1,"value":-8.07999992370605}]},{"path":"","type":"UnityEngine.Transform","propertyName":"m_LocalPosition.y","keyFrames":[{"inTangent":0,"outTangent":0,"tangentMode":10,"time":0,"value":0.910000026226044},{"inTangent":0,"outTangent":0,"tangentMode":10,"time":1,"value":0.910000026226044}]},{"path":"","type":"UnityEngine.Transform","propertyName":"m_LocalPosition.z","keyFrames":[{"inTangent":-7.66000032424927,"outTangent":-7.66000032424927,"tangentMode":10,"time":0,"value":-0.600000023841858},{"inTangent":-7.66000032424927,"outTangent":-7.66000032424927,"tangentMode":10,"time":1,"value":-8.26000022888184}]},{"path":"","type":"UnityEngine.Transform","propertyName":"m_LocalScale.z","keyFrames":[{"inTangent":0,"outTangent":0,"tangentMode":10,"time":0,"value":1},{"inTangent":0,"outTangent":0,"tangentMode":10,"time":1,"value":1}]},{"path":"","type":"UnityEngine.Transform","propertyName":"m_LocalScale.y","keyFrames":[{"inTangent":0,"outTangent":0,"tangentMode":10,"time":0,"value":1},{"inTangent":0,"outTangent":0,"tangentMode":10,"time":1,"value":1}]},{"path":"","type":"UnityEngine.Transform","propertyName":"m_LocalScale.x","keyFrames":[{"inTangent":0,"outTangent":0,"tangentMode":10,"time":0,"value":1},{"inTangent":0,"outTangent":0,"tangentMode":10,"time":1,"value":1}]},{"path":"","type":"UnityEngine.Transform","propertyName":"m_LocalRotation.x","keyFrames":[{"inTangent":0,"outTangent":0,"tangentMode":0,"time":0,"value":0},{"inTangent":0,"outTangent":0,"tangentMode":0,"time":0.0166666675359011,"value":0},{"inTangent":0,"outTangent":0,"tangentMode":0,"time":0.0333333350718021,"value":0},{"inTangent":0,"outTangent":0,"tangentMode":0,"time":0.0500000044703484,"value":0},{"inTangent":0,"outTangent":0,"tangentMode":0,"time":0.0666666701436043,"value":0},{"inTangent":0,"outTangent":0,"tangentMode":0,"time":0.0833333358168602,"value":0},{"inTangent":0,"outTangent":0,"tangentMode":0,"time":0.100000001490116,"value":0},{"inTangent":0,"outTangent":0,"tangentMode":0,"time":0.116666667163372,"value":0},{"inTangent":0,"outTangent":0,"tangentMode":0,"time":0.133333340287209,"value":0},{"inTangent":0,"outTangent":0,"tangentMode":0,"time":0.150000005960464,"value":0},{"inTangent":0,"outTangent":0,"tangentMode":0,"time":0.16666667163372,"value":0},{"inTangent":0,"outTangent":0,"tangentMode":0,"time":0.183333337306976,"value":0},{"inTangent":0,"outTangent":0,"tangentMode":0,"time":0.200000002980232,"value":0},{"inTangent":0,"outTangent":0,"tangentMode":0,"time":0.216666668653488,"value":0},{"inTangent":0,"outTangent":0,"tangentMode":0,"time":0.233333334326744,"value":0},{"inTangent":0,"outTangent":0,"tangentMode":0,"time":0.25,"value":0},{"inTangent":0,"outTangent":0,"tangentMode":0,"time":0.266666680574417,"value":0},{"inTangent":0,"outTangent":0,"tangentMode":0,"time":0.283333361148834,"value":0},{"inTangent":0,"outTangent":0,"tangentMode":0,"time":0.300000041723251,"value":0},{"inTangent":0,"outTangent":0,"tangentMode":0,"time":0.316666722297668,"value":0},{"inTangent":0,"outTangent":0,"tangentMode":0,"time":0.333333402872086,"value":0},{"inTangent":0,"outTangent":0,"tangentMode":0,"time":0.350000083446503,"value":0},{"inTangent":0,"outTangent":0,"tangentMode":0,"time":0.36666676402092,"value":0},{"inTangent":0,"outTangent":0,"tangentMode":0,"time":0.383333444595337,"value":0},{"inTangent":0,"outTangent":0,"tangentMode":0,"time":0.400000125169754,"value":0},{"inTangent":0,"outTangent":0,"tangentMode":0,"time":0.416666805744171,"value":0},{"inTangent":0,"outTangent":0,"tangentMode":0,"time":0.433333486318588,"value":0},{"inTangent":0,"outTangent":0,"tangentMode":0,"time":0.450000166893005,"value":0},{"inTangent":0,"outTangent":0,"tangentMode":0,"time":0.466666847467422,"value":0},{"inTangent":0,"outTangent":0,"tangentMode":0,"time":0.48333352804184,"value":0},{"inTangent":0,"outTangent":0,"tangentMode":0,"time":0.500000178813934,"value":0},{"inTangent":0,"outTangent":0,"tangentMode":0,"time":0.516666829586029,"value":0},{"inTangent":0,"outTangent":0,"tangentMode":0,"time":0.533333480358124,"value":0},{"inTangent":0,"outTangent":0,"tangentMode":0,"time":0.550000131130219,"value":0},{"inTangent":0,"outTangent":0,"tangentMode":0,"time":0.566666781902313,"value":0},{"inTangent":0,"outTangent":0,"tangentMode":0,"time":0.583333432674408,"value":0},{"inTangent":0,"outTangent":0,"tangentMode":0,"time":0.600000083446503,"value":0},{"inTangent":0,"outTangent":0,"tangentMode":0,"time":0.616666734218597,"value":0},{"inTangent":0,"outTangent":0,"tangentMode":0,"time":0.633333384990692,"value":0},{"inTangent":0,"outTangent":0,"tangentMode":0,"time":0.650000035762787,"value":0},{"inTangent":0,"outTangent":0,"tangentMode":0,"time":0.666666686534882,"value":0},{"inTangent":0,"outTangent":0,"tangentMode":0,"time":0.683333337306976,"value":0},{"inTangent":0,"outTangent":0,"tangentMode":0,"time":0.699999988079071,"value":0},{"inTangent":0,"outTangent":0,"tangentMode":0,"time":0.716666638851166,"value":0},{"inTangent":0,"outTangent":0,"tangentMode":0,"time":0.733333289623261,"value":0},{"inTangent":0,"outTangent":0,"tangentMode":0,"time":0.749999940395355,"value":0},{"inTangent":0,"outTangent":0,"tangentMode":0,"time":0.76666659116745,"value":0},{"inTangent":0,"outTangent":0,"tangentMode":0,"time":0.783333241939545,"value":0},{"inTangent":0,"outTangent":0,"tangentMode":0,"time":0.799999892711639,"value":0},{"inTangent":0,"outTangent":0,"tangentMode":0,"time":0.816666543483734,"value":0},{"inTangent":0,"outTangent":0,"tangentMode":0,"time":0.833333194255829,"value":0},{"inTangent":0,"outTangent":0,"tangentMode":0,"time":0.849999845027924,"value":0},{"inTangent":0,"outTangent":0,"tangentMode":0,"time":0.866666495800018,"value":0},{"inTangent":0,"outTangent":0,"tangentMode":0,"time":0.883333146572113,"value":0},{"inTangent":0,"outTangent":0,"tangentMode":0,"time":0.899999797344208,"value":0},{"inTangent":0,"outTangent":0,"tangentMode":0,"time":0.916666448116302,"value":0},{"inTangent":0,"outTangent":0,"tangentMode":0,"time":0.933333098888397,"value":0},{"inTangent":0,"outTangent":0,"tangentMode":0,"time":0.949999749660492,"value":0},{"inTangent":0,"outTangent":0,"tangentMode":0,"time":0.966666400432587,"value":0},{"inTangent":0,"outTangent":0,"tangentMode":0,"time":0.983333051204681,"value":0},{"inTangent":0,"outTangent":0,"tangentMode":0,"time":1,"value":0}]},{"path":"","type":"UnityEngine.Transform","propertyName":"m_LocalRotation.y","keyFrames":[{"inTangent":0,"outTangent":0,"tangentMode":0,"time":0,"value":0},{"inTangent":0,"outTangent":0,"tangentMode":0,"time":0.0166666675359011,"value":0},{"inTangent":0,"outTangent":0,"tangentMode":0,"time":0.0333333350718021,"value":0},{"inTangent":0,"outTangent":0,"tangentMode":0,"time":0.0500000044703484,"value":0},{"inTangent":0,"outTangent":0,"tangentMode":0,"time":0.0666666701436043,"value":0},{"inTangent":0,"outTangent":0,"tangentMode":0,"time":0.0833333358168602,"value":0},{"inTangent":0,"outTangent":0,"tangentMode":0,"time":0.100000001490116,"value":0},{"inTangent":0,"outTangent":0,"tangentMode":0,"time":0.116666667163372,"value":0},{"inTangent":0,"outTangent":0,"tangentMode":0,"time":0.133333340287209,"value":0},{"inTangent":0,"outTangent":0,"tangentMode":0,"time":0.150000005960464,"value":0},{"inTangent":0,"outTangent":0,"tangentMode":0,"time":0.16666667163372,"value":0},{"inTangent":0,"outTangent":0,"tangentMode":0,"time":0.183333337306976,"value":0},{"inTangent":0,"outTangent":0,"tangentMode":0,"time":0.200000002980232,"value":0},{"inTangent":0,"outTangent":0,"tangentMode":0,"time":0.216666668653488,"value":0},{"inTangent":0,"outTangent":0,"tangentMode":0,"time":0.233333334326744,"value":0},{"inTangent":0,"outTangent":0,"tangentMode":0,"time":0.25,"value":0},{"inTangent":0,"outTangent":0,"tangentMode":0,"time":0.266666680574417,"value":0},{"inTangent":0,"outTangent":0,"tangentMode":0,"time":0.283333361148834,"value":0},{"inTangent":0,"outTangent":0,"tangentMode":0,"time":0.300000041723251,"value":0},{"inTangent":0,"outTangent":0,"tangentMode":0,"time":0.316666722297668,"value":0},{"inTangent":0,"outTangent":0,"tangentMode":0,"time":0.333333402872086,"value":0},{"inTangent":0,"outTangent":0,"tangentMode":0,"time":0.350000083446503,"value":0},{"inTangent":0,"outTangent":0,"tangentMode":0,"time":0.36666676402092,"value":0},{"inTangent":0,"outTangent":0,"tangentMode":0,"time":0.383333444595337,"value":0},{"inTangent":0,"outTangent":0,"tangentMode":0,"time":0.400000125169754,"value":0},{"inTangent":0,"outTangent":0,"tangentMode":0,"time":0.416666805744171,"value":0},{"inTangent":0,"outTangent":0,"tangentMode":0,"time":0.433333486318588,"value":0},{"inTangent":0,"outTangent":0,"tangentMode":0,"time":0.450000166893005,"value":0},{"inTangent":0,"outTangent":0,"tangentMode":0,"time":0.466666847467422,"value":0},{"inTangent":0,"outTangent":0,"tangentMode":0,"time":0.48333352804184,"value":0},{"inTangent":0,"outTangent":0,"tangentMode":0,"time":0.500000178813934,"value":0},{"inTangent":0,"outTangent":0,"tangentMode":0,"time":0.516666829586029,"value":0},{"inTangent":0,"outTangent":0,"tangentMode":0,"time":0.533333480358124,"value":0},{"inTangent":0,"outTangent":0,"tangentMode":0,"time":0.550000131130219,"value":0},{"inTangent":0,"outTangent":0,"tangentMode":0,"time":0.566666781902313,"value":0},{"inTangent":0,"outTangent":0,"tangentMode":0,"time":0.583333432674408,"value":0},{"inTangent":0,"outTangent":0,"tangentMode":0,"time":0.600000083446503,"value":0},{"inTangent":0,"outTangent":0,"tangentMode":0,"time":0.616666734218597,"value":0},{"inTangent":0,"outTangent":0,"tangentMode":0,"time":0.633333384990692,"value":0},{"inTangent":0,"outTangent":0,"tangentMode":0,"time":0.650000035762787,"value":0},{"inTangent":0,"outTangent":0,"tangentMode":0,"time":0.666666686534882,"value":0},{"inTangent":0,"outTangent":0,"tangentMode":0,"time":0.683333337306976,"value":0},{"inTangent":0,"outTangent":0,"tangentMode":0,"time":0.699999988079071,"value":0},{"inTangent":0,"outTangent":0,"tangentMode":0,"time":0.716666638851166,"value":0},{"inTangent":0,"outTangent":0,"tangentMode":0,"time":0.733333289623261,"value":0},{"inTangent":0,"outTangent":0,"tangentMode":0,"time":0.749999940395355,"value":0},{"inTangent":0,"outTangent":0,"tangentMode":0,"time":0.76666659116745,"value":0},{"inTangent":0,"outTangent":0,"tangentMode":0,"time":0.783333241939545,"value":0},{"inTangent":0,"outTangent":0,"tangentMode":0,"time":0.799999892711639,"value":0},{"inTangent":0,"outTangent":0,"tangentMode":0,"time":0.816666543483734,"value":0},{"inTangent":0,"outTangent":0,"tangentMode":0,"time":0.833333194255829,"value":0},{"inTangent":0,"outTangent":0,"tangentMode":0,"time":0.849999845027924,"value":0},{"inTangent":0,"outTangent":0,"tangentMode":0,"time":0.866666495800018,"value":0},{"inTangent":0,"outTangent":0,"tangentMode":0,"time":0.883333146572113,"value":0},{"inTangent":0,"outTangent":0,"tangentMode":0,"time":0.899999797344208,"value":0},{"inTangent":0,"outTangent":0,"tangentMode":0,"time":0.916666448116302,"value":0},{"inTangent":0,"outTangent":0,"tangentMode":0,"time":0.933333098888397,"value":0},{"inTangent":0,"outTangent":0,"tangentMode":0,"time":0.949999749660492,"value":0},{"inTangent":0,"outTangent":0,"tangentMode":0,"time":0.966666400432587,"value":0},{"inTangent":0,"outTangent":0,"tangentMode":0,"time":0.983333051204681,"value":0},{"inTangent":0,"outTangent":0,"tangentMode":0,"time":1,"value":0}]},{"path":"","type":"UnityEngine.Transform","propertyName":"m_LocalRotation.z","keyFrames":[{"inTangent":0,"outTangent":0,"tangentMode":0,"time":0,"value":0},{"inTangent":0,"outTangent":0,"tangentMode":0,"time":0.0166666675359011,"value":0},{"inTangent":0,"outTangent":0,"tangentMode":0,"time":0.0333333350718021,"value":0},{"inTangent":0,"outTangent":0,"tangentMode":0,"time":0.0500000044703484,"value":0},{"inTangent":0,"outTangent":0,"tangentMode":0,"time":0.0666666701436043,"value":0},{"inTangent":0,"outTangent":0,"tangentMode":0,"time":0.0833333358168602,"value":0},{"inTangent":0,"outTangent":0,"tangentMode":0,"time":0.100000001490116,"value":0},{"inTangent":0,"outTangent":0,"tangentMode":0,"time":0.116666667163372,"value":0},{"inTangent":0,"outTangent":0,"tangentMode":0,"time":0.133333340287209,"value":0},{"inTangent":0,"outTangent":0,"tangentMode":0,"time":0.150000005960464,"value":0},{"inTangent":0,"outTangent":0,"tangentMode":0,"time":0.16666667163372,"value":0},{"inTangent":0,"outTangent":0,"tangentMode":0,"time":0.183333337306976,"value":0},{"inTangent":0,"outTangent":0,"tangentMode":0,"time":0.200000002980232,"value":0},{"inTangent":0,"outTangent":0,"tangentMode":0,"time":0.216666668653488,"value":0},{"inTangent":0,"outTangent":0,"tangentMode":0,"time":0.233333334326744,"value":0},{"inTangent":0,"outTangent":0,"tangentMode":0,"time":0.25,"value":0},{"inTangent":0,"outTangent":0,"tangentMode":0,"time":0.266666680574417,"value":0},{"inTangent":0,"outTangent":0,"tangentMode":0,"time":0.283333361148834,"value":0},{"inTangent":0,"outTangent":0,"tangentMode":0,"time":0.300000041723251,"value":0},{"inTangent":0,"outTangent":0,"tangentMode":0,"time":0.316666722297668,"value":0},{"inTangent":0,"outTangent":0,"tangentMode":0,"time":0.333333402872086,"value":0},{"inTangent":0,"outTangent":0,"tangentMode":0,"time":0.350000083446503,"value":0},{"inTangent":0,"outTangent":0,"tangentMode":0,"time":0.36666676402092,"value":0},{"inTangent":0,"outTangent":0,"tangentMode":0,"time":0.383333444595337,"value":0},{"inTangent":0,"outTangent":0,"tangentMode":0,"time":0.400000125169754,"value":0},{"inTangent":0,"outTangent":0,"tangentMode":0,"time":0.416666805744171,"value":0},{"inTangent":0,"outTangent":0,"tangentMode":0,"time":0.433333486318588,"value":0},{"inTangent":0,"outTangent":0,"tangentMode":0,"time":0.450000166893005,"value":0},{"inTangent":0,"outTangent":0,"tangentMode":0,"time":0.466666847467422,"value":0},{"inTangent":0,"outTangent":0,"tangentMode":0,"time":0.48333352804184,"value":0},{"inTangent":0,"outTangent":0,"tangentMode":0,"time":0.500000178813934,"value":0},{"inTangent":0,"outTangent":0,"tangentMode":0,"time":0.516666829586029,"value":0},{"inTangent":0,"outTangent":0,"tangentMode":0,"time":0.533333480358124,"value":0},{"inTangent":0,"outTangent":0,"tangentMode":0,"time":0.550000131130219,"value":0},{"inTangent":0,"outTangent":0,"tangentMode":0,"time":0.566666781902313,"value":0},{"inTangent":0,"outTangent":0,"tangentMode":0,"time":0.583333432674408,"value":0},{"inTangent":0,"outTangent":0,"tangentMode":0,"time":0.600000083446503,"value":0},{"inTangent":0,"outTangent":0,"tangentMode":0,"time":0.616666734218597,"value":0},{"inTangent":0,"outTangent":0,"tangentMode":0,"time":0.633333384990692,"value":0},{"inTangent":0,"outTangent":0,"tangentMode":0,"time":0.650000035762787,"value":0},{"inTangent":0,"outTangent":0,"tangentMode":0,"time":0.666666686534882,"value":0},{"inTangent":0,"outTangent":0,"tangentMode":0,"time":0.683333337306976,"value":0},{"inTangent":0,"outTangent":0,"tangentMode":0,"time":0.699999988079071,"value":0},{"inTangent":0,"outTangent":0,"tangentMode":0,"time":0.716666638851166,"value":0},{"inTangent":0,"outTangent":0,"tangentMode":0,"time":0.733333289623261,"value":0},{"inTangent":0,"outTangent":0,"tangentMode":0,"time":0.749999940395355,"value":0},{"inTangent":0,"outTangent":0,"tangentMode":0,"time":0.76666659116745,"value":0},{"inTangent":0,"outTangent":0,"tangentMode":0,"time":0.783333241939545,"value":0},{"inTangent":0,"outTangent":0,"tangentMode":0,"time":0.799999892711639,"value":0},{"inTangent":0,"outTangent":0,"tangentMode":0,"time":0.816666543483734,"value":0},{"inTangent":0,"outTangent":0,"tangentMode":0,"time":0.833333194255829,"value":0},{"inTangent":0,"outTangent":0,"tangentMode":0,"time":0.849999845027924,"value":0},{"inTangent":0,"outTangent":0,"tangentMode":0,"time":0.866666495800018,"value":0},{"inTangent":0,"outTangent":0,"tangentMode":0,"time":0.883333146572113,"value":0},{"inTangent":0,"outTangent":0,"tangentMode":0,"time":0.899999797344208,"value":0},{"inTangent":0,"outTangent":0,"tangentMode":0,"time":0.916666448116302,"value":0},{"inTangent":0,"outTangent":0,"tangentMode":0,"time":0.933333098888397,"value":0},{"inTangent":0,"outTangent":0,"tangentMode":0,"time":0.949999749660492,"value":0},{"inTangent":0,"outTangent":0,"tangentMode":0,"time":0.966666400432587,"value":0},{"inTangent":0,"outTangent":0,"tangentMode":0,"time":0.983333051204681,"value":0},{"inTangent":0,"outTangent":0,"tangentMode":0,"time":1,"value":0}]},{"path":"","type":"UnityEngine.Transform","propertyName":"m_LocalRotation.w","keyFrames":[{"inTangent":0,"outTangent":0,"tangentMode":0,"time":0,"value":1},{"inTangent":0,"outTangent":0,"tangentMode":0,"time":0.0166666675359011,"value":1},{"inTangent":0,"outTangent":0,"tangentMode":0,"time":0.0333333350718021,"value":1},{"inTangent":0,"outTangent":0,"tangentMode":0,"time":0.0500000044703484,"value":1},{"inTangent":0,"outTangent":0,"tangentMode":0,"time":0.0666666701436043,"value":1},{"inTangent":0,"outTangent":0,"tangentMode":0,"time":0.0833333358168602,"value":1},{"inTangent":0,"outTangent":0,"tangentMode":0,"time":0.100000001490116,"value":1},{"inTangent":0,"outTangent":0,"tangentMode":0,"time":0.116666667163372,"value":1},{"inTangent":0,"outTangent":0,"tangentMode":0,"time":0.133333340287209,"value":1},{"inTangent":0,"outTangent":0,"tangentMode":0,"time":0.150000005960464,"value":1},{"inTangent":0,"outTangent":0,"tangentMode":0,"time":0.16666667163372,"value":1},{"inTangent":0,"outTangent":0,"tangentMode":0,"time":0.183333337306976,"value":1},{"inTangent":0,"outTangent":0,"tangentMode":0,"time":0.200000002980232,"value":1},{"inTangent":0,"outTangent":0,"tangentMode":0,"time":0.216666668653488,"value":1},{"inTangent":0,"outTangent":0,"tangentMode":0,"time":0.233333334326744,"value":1},{"inTangent":0,"outTangent":0,"tangentMode":0,"time":0.25,"value":1},{"inTangent":0,"outTangent":0,"tangentMode":0,"time":0.266666680574417,"value":1},{"inTangent":0,"outTangent":0,"tangentMode":0,"time":0.283333361148834,"value":1},{"inTangent":0,"outTangent":0,"tangentMode":0,"time":0.300000041723251,"value":1},{"inTangent":0,"outTangent":0,"tangentMode":0,"time":0.316666722297668,"value":1},{"inTangent":0,"outTangent":0,"tangentMode":0,"time":0.333333402872086,"value":1},{"inTangent":0,"outTangent":0,"tangentMode":0,"time":0.350000083446503,"value":1},{"inTangent":0,"outTangent":0,"tangentMode":0,"time":0.36666676402092,"value":1},{"inTangent":0,"outTangent":0,"tangentMode":0,"time":0.383333444595337,"value":1},{"inTangent":0,"outTangent":0,"tangentMode":0,"time":0.400000125169754,"value":1},{"inTangent":0,"outTangent":0,"tangentMode":0,"time":0.416666805744171,"value":1},{"inTangent":0,"outTangent":0,"tangentMode":0,"time":0.433333486318588,"value":1},{"inTangent":0,"outTangent":0,"tangentMode":0,"time":0.450000166893005,"value":1},{"inTangent":0,"outTangent":0,"tangentMode":0,"time":0.466666847467422,"value":1},{"inTangent":0,"outTangent":0,"tangentMode":0,"time":0.48333352804184,"value":1},{"inTangent":0,"outTangent":0,"tangentMode":0,"time":0.500000178813934,"value":1},{"inTangent":0,"outTangent":0,"tangentMode":0,"time":0.516666829586029,"value":1},{"inTangent":0,"outTangent":0,"tangentMode":0,"time":0.533333480358124,"value":1},{"inTangent":0,"outTangent":0,"tangentMode":0,"time":0.550000131130219,"value":1},{"inTangent":0,"outTangent":0,"tangentMode":0,"time":0.566666781902313,"value":1},{"inTangent":0,"outTangent":0,"tangentMode":0,"time":0.583333432674408,"value":1},{"inTangent":0,"outTangent":0,"tangentMode":0,"time":0.600000083446503,"value":1},{"inTangent":0,"outTangent":0,"tangentMode":0,"time":0.616666734218597,"value":1},{"inTangent":0,"outTangent":0,"tangentMode":0,"time":0.633333384990692,"value":1},{"inTangent":0,"outTangent":0,"tangentMode":0,"time":0.650000035762787,"value":1},{"inTangent":0,"outTangent":0,"tangentMode":0,"time":0.666666686534882,"value":1},{"inTangent":0,"outTangent":0,"tangentMode":0,"time":0.683333337306976,"value":1},{"inTangent":0,"outTangent":0,"tangentMode":0,"time":0.699999988079071,"value":1},{"inTangent":0,"outTangent":0,"tangentMode":0,"time":0.716666638851166,"value":1},{"inTangent":0,"outTangent":0,"tangentMode":0,"time":0.733333289623261,"value":1},{"inTangent":0,"outTangent":0,"tangentMode":0,"time":0.749999940395355,"value":1},{"inTangent":0,"outTangent":0,"tangentMode":0,"time":0.76666659116745,"value":1},{"inTangent":0,"outTangent":0,"tangentMode":0,"time":0.783333241939545,"value":1},{"inTangent":0,"outTangent":0,"tangentMode":0,"time":0.799999892711639,"value":1},{"inTangent":0,"outTangent":0,"tangentMode":0,"time":0.816666543483734,"value":1},{"inTangent":0,"outTangent":0,"tangentMode":0,"time":0.833333194255829,"value":1},{"inTangent":0,"outTangent":0,"tangentMode":0,"time":0.849999845027924,"value":1},{"inTangent":0,"outTangent":0,"tangentMode":0,"time":0.866666495800018,"value":1},{"inTangent":0,"outTangent":0,"tangentMode":0,"time":0.883333146572113,"value":1},{"inTangent":0,"outTangent":0,"tangentMode":0,"time":0.899999797344208,"value":1},{"inTangent":0,"outTangent":0,"tangentMode":0,"time":0.916666448116302,"value":1},{"inTangent":0,"outTangent":0,"tangentMode":0,"time":0.933333098888397,"value":1},{"inTangent":0,"outTangent":0,"tangentMode":0,"time":0.949999749660492,"value":1},{"inTangent":0,"outTangent":0,"tangentMode":0,"time":0.966666400432587,"value":1},{"inTangent":0,"outTangent":0,"tangentMode":0,"time":0.983333051204681,"value":1},{"inTangent":0,"outTangent":0,"tangentMode":0,"time":1,"value":1}]},{"path":"","type":"UnityEngine.MeshRenderer","propertyName":"material._Color.r","keyFrames":[{"inTangent":0,"outTangent":0,"tangentMode":10,"time":0,"value":1},{"inTangent":0,"outTangent":0,"tangentMode":10,"time":1,"value":1}]},{"path":"","type":"UnityEngine.MeshRenderer","propertyName":"material._Color.g","keyFrames":[{"inTangent":0,"outTangent":0,"tangentMode":10,"time":0,"value":1},{"inTangent":0,"outTangent":0,"tangentMode":10,"time":1,"value":1}]},{"path":"","type":"UnityEngine.MeshRenderer","propertyName":"material._Color.b","keyFrames":[{"inTangent":0,"outTangent":0,"tangentMode":10,"time":0,"value":1},{"inTangent":0,"outTangent":0,"tangentMode":10,"time":1,"value":1}]},{"path":"","type":"UnityEngine.MeshRenderer","propertyName":"material._Color.a","keyFrames":[{"inTangent":0,"outTangent":0,"tangentMode":10,"time":0,"value":0.5},{"inTangent":0,"outTangent":0,"tangentMode":10,"time":1,"value":0.5}]},{"path":"","type":"UnityEngine.MeshRenderer","propertyName":"material._MainTex_ST.x","keyFrames":[{"inTangent":0,"outTangent":0,"tangentMode":10,"time":0,"value":1},{"inTangent":0,"outTangent":0,"tangentMode":10,"time":1,"value":1}]},{"path":"","type":"UnityEngine.MeshRenderer","propertyName":"material._MainTex_ST.y","keyFrames":[{"inTangent":0,"outTangent":0,"tangentMode":10,"time":0,"value":1},{"inTangent":0,"outTangent":0,"tangentMode":10,"time":1,"value":1}]},{"path":"","type":"UnityEngine.MeshRenderer","propertyName":"material._MainTex_ST.z","keyFrames":[{"inTangent":0,"outTangent":0,"tangentMode":10,"time":0,"value":0},{"inTangent":0,"outTangent":0,"tangentMode":10,"time":1,"value":0}]},{"path":"","type":"UnityEngine.MeshRenderer","propertyName":"material._MainTex_ST.w","keyFrames":[{"inTangent":0,"outTangent":0,"tangentMode":10,"time":0,"value":0},{"inTangent":0,"outTangent":0,"tangentMode":10,"time":1,"value":0}]},{"path":"","type":"UnityEngine.MeshRenderer","propertyName":"material._MainTex_TexelSize.x","keyFrames":[{"inTangent":0,"outTangent":0,"tangentMode":10,"time":0,"value":1},{"inTangent":0,"outTangent":0,"tangentMode":10,"time":1,"value":1}]},{"path":"","type":"UnityEngine.MeshRenderer","propertyName":"material._MainTex_TexelSize.y","keyFrames":[{"inTangent":0,"outTangent":0,"tangentMode":10,"time":0,"value":1},{"inTangent":0,"outTangent":0,"tangentMode":10,"time":1,"value":1}]},{"path":"","type":"UnityEngine.MeshRenderer","propertyName":"material._MainTex_TexelSize.z","keyFrames":[{"inTangent":0,"outTangent":0,"tangentMode":10,"time":0,"value":1},{"inTangent":0,"outTangent":0,"tangentMode":10,"time":1,"value":1}]},{"path":"","type":"UnityEngine.MeshRenderer","propertyName":"material._MainTex_TexelSize.w","keyFrames":[{"inTangent":0,"outTangent":0,"tangentMode":10,"time":0,"value":1},{"inTangent":0,"outTangent":0,"tangentMode":10,"time":1,"value":1}]}]}