{
	"cls": "transform2D",
	"insid": -6716,
	"prefab": "",
	"layer": 5,
	"tag": "Untagged",
	"name": "Panel",
	"isStatic": false,
	"isMask": false,
	"_visible": true,
	"layoutState": 48,
	"layoutValueMap": {
		"16": 0,
		"32": 0
	},
	"layoutPercentState": 0,
	"width": 100,
	"height": 134,
	"pivot": {
		"cls": "vector2",
		"x": 0.5,
		"y": 0.5
	},
	"localTranslate": {
		"cls": "vector2",
		"x": -406,
		"y": -219.5
	},
	"localScale": {
		"cls": "vector2",
		"x": 1,
		"y": 1
	},
	"localRotate": 0,
	"components": [
		{
			"cls": "image2D",
			"color": {
				"cls": "color",
				"r": 1,
				"g": 1,
				"b": 1,
				"a": 0.3919999897480011
			},
			"imageType": 0,
			"fillMethod": 0,
			"fillAmmount": 1,
			"_spriteName": "spritesheet.atlas.json_Body",
			"_imageBorder": {
				"cls": "border",
				"l": 0,
				"t": 0,
				"r": 0,
				"b": 0
			}
		}],
	"children": []
}