{"Text.cprefab.json":"{\n\t\"cls\": \"transform2D\",\n\t\"insid\": 14544,\n\t\"prefab\": \"\",\n\t\"layer\": 5,\n\t\"tag\": \"Untagged\",\n\t\"name\": \"Text\",\n\t\"isStatic\": false,\n\t\"isMask\": false,\n\t\"_visible\": true,\n\t\"width\": 160,\n\t\"height\": 30,\n\t\"pivot\": {\n\t\t\"cls\": \"vector2\",\n\t\t\"x\": 0.5,\n\t\t\"y\": 0.5\n\t},\n\t\"localTranslate\": {\n\t\t\"cls\": \"vector2\",\n\t\t\"x\": -109,\n\t\t\"y\": 203.39999389648438\n\t},\n\t\"localScale\": {\n\t\t\"cls\": \"vector2\",\n\t\t\"x\": 1,\n\t\t\"y\": 1\n\t},\n\t\"localRotate\": 0,\n\t\"layoutState\": 48,\n\t\"layoutValueMap\": {\n\t\t\"16\": -109,\n\t\t\"32\": -203.39999389648438\n\t},\n\t\"layoutPercentState\": 0,\n\t\"components\": [\n\t\t{\n\t\t\t\"cls\": \"label\",\n\t\t\t\"text\": \"New TextNew Text\",\n\t\t\t\"_fontName\": \"defFont.font.json\",\n\t\t\t\"fontsize\": 16,\n\t\t\t\"linespace\": 1,\n\t\t\t\"horizontalOverflow\": false,\n\t\t\t\"verticalOverflow\": false,\n\t\t\t\"color\": {\n\t\t\t\t\"cls\": \"color\",\n\t\t\t\t\"r\": 0.9866247177124023,\n\t\t\t\t\"g\": 1,\n\t\t\t\t\"b\": 0,\n\t\t\t\t\"a\": 1\n\t\t\t},\n\t\t\t\"color2\": {\n\t\t\t\t\"cls\": \"color\",\n\t\t\t\t\"r\": 0,\n\t\t\t\t\"g\": 0,\n\t\t\t\t\"b\": 0.5,\n\t\t\t\t\"a\": 0.5\n\t\t\t},\n\t\t\t\"verticalType\": 1,\n\t\t\t\"horizontalType\": 1\n\t\t}],\n\t\"children\": []\n}"}